splitme/__init__.py
splitme/__main__.py
splitme/cli.py
splitme/config.py
splitme/core.py
splitme/errors.py
splitme/logger.py
splitme/validators.py
splitme/generators/__init__.py
splitme/generators/mintlify/__init__.py
splitme/generators/mkdocs/__init__.py
splitme/generators/mkdocs/config.py
splitme/tools/__init__.py
splitme/tools/html/__init__.py
splitme/tools/markdown/__init__.py
splitme/tools/markdown/link_validator.py
splitme/tools/markdown/reflink_converter.py
splitme/tools/markdown/reflink_extractor.py
splitme/utils/__init__.py
splitme/utils/file_handler.py
splitme/utils/filename_sanitizer.py
splitme-0.1.11.dist-info/METADATA
splitme-0.1.11.dist-info/WHEEL
splitme-0.1.11.dist-info/entry_points.txt
splitme-0.1.11.dist-info/licenses/LICENSE
splitme-0.1.11.dist-info/RECORD
