Metadata-Version: 2.4
Name: splitme
Version: 0.1.11
Summary: ⌖ Markdown tools for modular docs.
Project-URL: Homepage, https://github.com/eli64s/splitme
Author-email: Eli Salamie <egsalamie@gmail.com>
License-Expression: MIT
License-File: LICENSE
Keywords: ai,devtools,docs,documentation,documentation-tool,markdown,markdown-parser,markdown-split,mkdocs,python,readme,reference-links,reflinks
Classifier: Development Status :: 3 - Alpha
Classifier: Framework :: Pydantic
Classifier: Framework :: Pytest
Classifier: Intended Audience :: Developers
Classifier: License :: OSI Approved :: MIT License
Classifier: Operating System :: OS Independent
Classifier: Programming Language :: Python :: 3 :: Only
Classifier: Programming Language :: Python :: 3.9
Classifier: Programming Language :: Python :: 3.10
Classifier: Programming Language :: Python :: 3.11
Classifier: Programming Language :: Python :: 3.12
Classifier: Programming Language :: Python :: 3.13
Classifier: Programming Language :: Python :: 3.14
Classifier: Topic :: Software Development :: Documentation
Classifier: Topic :: Software Development :: Libraries
Classifier: Topic :: Software Development :: Libraries :: Python Modules
Classifier: Typing :: Typed
Requires-Python: <=3.14,>=3.9
Requires-Dist: mistletoe>=1.4.0
Requires-Dist: pydantic-settings>=2.6.1
Requires-Dist: pydantic>=2.10.3
Requires-Dist: pyyaml>=6.0.2
Requires-Dist: requests>=2.32.3
Requires-Dist: rich>=13.9.4
Requires-Dist: toml>=0.10.2; python_full_version < '3.11'
Provides-Extra: ai
Requires-Dist: pydantic-ai>=0.0.15; extra == 'ai'
Provides-Extra: docs
Requires-Dist: mkdocs-material>=9.5.47; extra == 'docs'
Requires-Dist: mkdocs>=1.6.1; extra == 'docs'
